adaptio/__init__.py
adaptio/adaptive_async_concurrency_limiter.py
adaptio/adjustable_semaphore.py
adaptio/decorator_utils.py
adaptio/log_utils.py
adaptio/loop_local_lock.py
adaptio/loop_local_semaphore.py
adaptio/py.typed
adaptio/raise_on_aiohttp_overload.py
adaptio/raise_on_overload_by_guessing.py
adaptio/with_adaptive_retry.py
adaptio/with_async_control.py
adaptio-0.7.0.dist-info/METADATA
adaptio-0.7.0.dist-info/WHEEL
adaptio-0.7.0.dist-info/RECORD
