Metadata-Version: 2.4
Name: adaptio
Version: 0.7.0
Summary: Adaptio 是一个基于 Python asyncio 的智能并发控制工具。它借鉴了 TCP 拥塞控制算法的思想，可以根据系统负载动态调整并发任务的数量，从而优化任务吞吐量并防止过载。此外，还提供了一个装饰器，当任务因系统过载失败时自动重试。
Project-URL: Homepage, https://github.com/Haskely/adaptio
Project-URL: Bug Reports, https://github.com/Haskely/adaptio/issues
Project-URL: Source, https://github.com/Haskely/adaptio
Author-email: Haskely <Haskely@live.com>
Requires-Python: >=3.10
Requires-Dist: aiohttp
Requires-Dist: colorlog
Requires-Dist: loguru
